.gitignore
.travis.yml
CHANGELOG.rst
LICENSE
MANIFEST.in
Pipfile
README.rst
setup.cfg
setup.py
docs/Makefile
docs/source/changelog.rst
docs/source/conf.py
docs/source/docs.rst
docs/source/index.rst
docs/source/othoz-logo.png
paragraph/__init__.py
paragraph/session.py
paragraph/types.py
paragraph.egg-info/PKG-INFO
paragraph.egg-info/SOURCES.txt
paragraph.egg-info/dependency_links.txt
paragraph.egg-info/requires.txt
paragraph.egg-info/top_level.txt
paragraph/tests/__init__.py
paragraph/tests/test_session.py
paragraph/tests/test_types.py