Metadata-Version: 2.1
Name: paragraph
Version: 1.1.0
Summary: A computation graph micro-framework providing seamless lazy and concurrent evaluation.
Home-page: https://github.com/Othoz/paragraph
Author: Othoz GmbH
Author-email: bourguignon@othoz.com
License: MIT
Project-URL: Bug Tracker, https://github.com/Othoz/paragraph/issues
Project-URL: Documentation, http://paragraph.readthedocs.io/en/latest/
Keywords: computation graph,concurrent,lazy
Platform: UNKNOWN
Classifier: Development Status :: 4 - Beta
Classifier: Intended Audience :: Developers
Classifier: License :: OSI Approved :: MIT License
Classifier: Operating System :: OS Independent
Classifier: Programming Language :: Python
Classifier: Programming Language :: Python :: 3
Classifier: Programming Language :: Python :: 3.6
Classifier: Programming Language :: Python :: 3.7
Classifier: Programming Language :: Python :: 3.8
Classifier: Programming Language :: Python :: Implementation
Requires-Python: >=3.6
